LICENSE
README.md
pyproject.toml
setup.py
pythondia/ObjectHelpers.py
pythondia/__init__.py
pythondia/_once.py
pythondia/objects.py
pythondia.egg-info/PKG-INFO
pythondia.egg-info/SOURCES.txt
pythondia.egg-info/dependency_links.txt
pythondia.egg-info/requires.txt
pythondia.egg-info/top_level.txt
pythondia/objects/__init__.py
pythondia/objects/Database/Table.py
pythondia/objects/Database/__init__.py
pythondia/objects/UML/Class.py
pythondia/objects/UML/__init__.py
tests/__init__.py
tests/diapython.py