Metadata-Version: 2.1
Name: pythondia
Version: 1.0.1
Summary: Python dia helpers to generate diagrams in dia from python
Home-page: http://github.com/sosie-js/python-dia
Author: Olivier Lutzwiller
Author-email: sosie@sos-productions.com
License: GPL
Keywords: dia python diagram helper
Platform: UNKNOWN
Classifier: Development Status :: 4 - Beta
Classifier: Intended Audience :: Developers
Classifier: Operating System :: OS Independent
Classifier: Programming Language :: Python :: 3
Classifier: Topic :: Multimedia :: Graphics :: Presentation
Classifier: Topic :: Software Development :: Libraries
Requires-Python: >=3.6
